blackice/__init__.py
blackice/baseline.py
blackice/cli.py
blackice/detector.py
blackice/deviation.py
blackice/metrics.py
blackice/persistence.py
blackice/pipeline.py
blackice/state.py
blackice-1.1.1.dist-info/licenses/LICENSE
blackice-1.1.1.dist-info/METADATA
blackice-1.1.1.dist-info/WHEEL
blackice-1.1.1.dist-info/entry_points.txt
blackice-1.1.1.dist-info/top_level.txt
blackice-1.1.1.dist-info/RECORD
