Metadata-Version: 2.4
Name: blackice
Version: 1.1.1
Summary: Streaming Regime Detection for Infrastructure. Independent Signal Engineering Library (Not associated with BlackIce Forensics/Databricks).
Author-email: Mihir Maru <mihir@example.com>
Project-URL: Homepage, https://github.com/Mihirmaru22/BLACKICE
Classifier: Programming Language :: Python :: 3
Classifier: License :: OSI Approved :: MIT License
Classifier: Operating System :: OS Independent
Requires-Python: >=3.10
License-File: LICENSE
Requires-Dist: pandas>=2.0.0
Requires-Dist: pyyaml>=6.0
Dynamic: license-file
